Dino/__init__.py
Dino/_main.py
DinoMint-0.7.dist-info/METADATA
DinoMint-0.7.dist-info/WHEEL
DinoMint-0.7.dist-info/top_level.txt
DinoMint-0.7.dist-info/RECORD
